becca/LICENSE
becca/__init__.py
becca/actor.py
becca/actor_numba.py
becca/affect.py
becca/base_world.py
becca/brain.py
becca/cat_tree.py
becca/connector.py
becca/discretizer.py
becca/featurizer.py
becca/input_filter.py
becca/model.py
becca/model_numba.py
becca/num_cat_tree_node.py
becca/postprocessor.py
becca/preprocessor.py
becca/str_cat_tree_node.py
becca/str_cat_utils.py
becca/tools.py
becca/ziptie.py
becca/ziptie_numba.py
becca-0.10.1.dist-info/METADATA
becca-0.10.1.dist-info/RECORD
becca-0.10.1.dist-info/WHEEL
becca-0.10.1.dist-info/top_level.txt
